pointscan/Makefile
pointscan/__init__.py
pointscan/app.py
pointscan/client.py
pointscan/regex.py
pointscan/remove.py
pointscan/replace.py
pointscan/scan.py
pointscan/split.py
pointscan/trim.py
pointscan-0.1.2.dist-info/entry_points.txt
pointscan-0.1.2.dist-info/LICENSE
pointscan-0.1.2.dist-info/WHEEL
pointscan-0.1.2.dist-info/METADATA
pointscan-0.1.2.dist-info/RECORD
