Metadata-Version: 2.1
Name: pointscan
Version: 0.1.2
Summary: Library for scanning BACnet points
License: BSD-3-Clause
Author: Gabe Fierro
Author-email: gtfierro@cs.berkeley.edu
Requires-Python: >=3.6,<4.0
Classifier: License :: OSI Approved :: BSD License
Classifier: Programming Language :: Python :: 3
Classifier: Programming Language :: Python :: 3.6
Classifier: Programming Language :: Python :: 3.7
Requires-Dist: BAC0 (>=19.9,<20.0)
Requires-Dist: Flask (>=1.1,<2.0)
Requires-Dist: click (>=7.0,<8.0)
Requires-Dist: pandas (>=0.25.3,<0.26.0)
Requires-Dist: requests (>=2.22,<3.0)
